AUTHORS
COPYING
MANIFEST.in
README.rst
setup.py
lib/xssd/__init__.py
lib/xssd/base.py
lib/xssd/errors.py
lib/xssd/validator.py
lib/xssd.egg-info/PKG-INFO
lib/xssd.egg-info/SOURCES.txt
lib/xssd.egg-info/dependency_links.txt
lib/xssd.egg-info/top_level.txt
lib/xssd/parse/__init__.py
lib/xssd/parse/xmlsd.py
tests/__init__.py
tests/base_tests.py
tests/test_all.py
tests/test_basic.py
tests/test_errors.py
tests/test_file_base.py
tests/test_flat_data.py
tests/test_load.py
tests/test_logic.py
tests/test_matched.py
tests/test_occurs.py
tests/test_schema.py
tests/test_xml.py
tests/data/XMLSchema.dtd
tests/data/broken.xsd
tests/data/definition0.xsd
tests/data/definition1.json
tests/data/definition1.xsd
tests/data/definition2.xsd
tests/data/file1.json
tests/data/file1.xml
tests/data/file2.json
tests/data/file2.xml
tests/data/file3.xml
tests/data/schema.xsd
tests/data/screamer.xsd
tests/data/smallest.xsd