Metadata-Version: 1.1
Name: xssd
Version: 0.9.2
Summary: Validating python structures based on XSD Subset rules.
Home-page: UNKNOWN
Author: Martin Owens
Author-email: doctormo@gmail.com
License: GPLv3
Platform: linux
Classifier: Development Status :: 5 - Production/Stable
Classifier: Development Status :: 6 - Mature
Classifier: Intended Audience :: Developers
Classifier: Intended Audience :: Information Technology
Classifier: Intended Audience :: System Administrators
Classifier: License :: OSI Approved :: GNU Lesser General Public License v3 or later (LGPLv3+)
Classifier: Operating System :: POSIX
Classifier: Operating System :: POSIX :: Linux
Classifier: Operating System :: POSIX :: SunOS/Solaris
Classifier: Programming Language :: Python
Classifier: Programming Language :: Python :: 3.6
